{
  "hash": "edc0eddb",
  "configHash": "ccf57085",
  "lockfileHash": "060a4d0f",
  "browserHash": "ba41e1b5",
  "optimized": {
    "react": {
      "src": "../../node_modules/react/index.js",
      "file": "react.js",
      "fileHash": "12723ccb",
      "needsInterop": true
    },
    "react-dom/client": {
      "src": "../../node_modules/react-dom/client.js",
      "file": "react-dom_client.js",
      "fileHash": "9002d08e",
      "needsInterop": true
    },
    "react-router-dom": {
      "src": "../../node_modules/react-router-dom/dist/index.js",
      "file": "react-router-dom.js",
      "fileHash": "532857c8",
      "needsInterop": false
    },
    "@douyinfe/semi-ui": {
      "src": "../../node_modules/@douyinfe/semi-ui/lib/es/index.js",
      "file": "@douyinfe_semi-ui.js",
      "fileHash": "ec02ba3f",
      "needsInterop": false
    },
    "react-i18next": {
      "src": "../../node_modules/react-i18next/dist/es/index.js",
      "file": "react-i18next.js",
      "fileHash": "f39e06ec",
      "needsInterop": false
    },
    "@douyinfe/semi-ui/lib/es/locale/source/zh_CN": {
      "src": "../../node_modules/@douyinfe/semi-ui/lib/es/locale/source/zh_CN.js",
      "file": "@douyinfe_semi-ui_lib_es_locale_source_zh_CN.js",
      "fileHash": "f48fe33b",
      "needsInterop": false
    },
    "@douyinfe/semi-ui/lib/es/locale/source/en_GB": {
      "src": "../../node_modules/@douyinfe/semi-ui/lib/es/locale/source/en_GB.js",
      "file": "@douyinfe_semi-ui_lib_es_locale_source_en_GB.js",
      "fileHash": "709e5480",
      "needsInterop": false
    },
    "i18next": {
      "src": "../../node_modules/i18next/dist/esm/i18next.js",
      "file": "i18next.js",
      "fileHash": "2f9081e1",
      "needsInterop": false
    },
    "i18next-browser-languagedetector": {
      "src": "../../node_modules/i18next-browser-languagedetector/dist/esm/i18nextBrowserLanguageDetector.js",
      "file": "i18next-browser-languagedetector.js",
      "fileHash": "6e5c9f5f",
      "needsInterop": false
    },
    "react-toastify": {
      "src": "../../node_modules/react-toastify/dist/react-toastify.esm.mjs",
      "file": "react-toastify.js",
      "fileHash": "bc3075b3",
      "needsInterop": false
    },
    "history": {
      "src": "../../node_modules/history/index.js",
      "file": "history.js",
      "fileHash": "ea17a586",
      "needsInterop": false
    },
    "axios": {
      "src": "../../node_modules/axios/index.js",
      "file": "axios.js",
      "fileHash": "7f7b6863",
      "needsInterop": false
    },
    "lucide-react": {
      "src": "../../node_modules/lucide-react/dist/esm/lucide-react.js",
      "file": "lucide-react.js",
      "fileHash": "d2658e6a",
      "needsInterop": false
    },
    "@douyinfe/semi-icons": {
      "src": "../../node_modules/@douyinfe/semi-icons/lib/es/index.js",
      "file": "@douyinfe_semi-icons.js",
      "fileHash": "b076565d",
      "needsInterop": false
    },
    "@douyinfe/semi-illustrations": {
      "src": "../../node_modules/@douyinfe/semi-illustrations/lib/es/index.js",
      "file": "@douyinfe_semi-illustrations.js",
      "fileHash": "636ec15d",
      "needsInterop": false
    },
    "marked": {
      "src": "../../node_modules/marked/lib/marked.esm.js",
      "file": "marked.js",
      "fileHash": "09922f1d",
      "needsInterop": false
    },
    "react-turnstile": {
      "src": "../../node_modules/react-turnstile/dist/index.js",
      "file": "react-turnstile.js",
      "fileHash": "54e5139c",
      "needsInterop": true
    },
    "@douyinfe/semi-ui/lib/es/typography/title": {
      "src": "../../node_modules/@douyinfe/semi-ui/lib/es/typography/title.js",
      "file": "@douyinfe_semi-ui_lib_es_typography_title.js",
      "fileHash": "53ccbc32",
      "needsInterop": false
    },
    "@douyinfe/semi-ui/lib/es/typography/text": {
      "src": "../../node_modules/@douyinfe/semi-ui/lib/es/typography/text.js",
      "file": "@douyinfe_semi-ui_lib_es_typography_text.js",
      "fileHash": "9078fb44",
      "needsInterop": false
    },
    "react-telegram-login": {
      "src": "../../node_modules/react-telegram-login/build/index.js",
      "file": "react-telegram-login.js",
      "fileHash": "5417f306",
      "needsInterop": true
    },
    "react-icons/si": {
      "src": "../../node_modules/react-icons/si/index.mjs",
      "file": "react-icons_si.js",
      "fileHash": "b2d63a12",
      "needsInterop": false
    },
    "react-telegram-login/src": {
      "src": "../../node_modules/react-telegram-login/src/index.js",
      "file": "react-telegram-login_src.js",
      "fileHash": "53210836",
      "needsInterop": false
    },
    "unist-util-visit": {
      "src": "../../node_modules/unist-util-visit/index.js",
      "file": "unist-util-visit.js",
      "fileHash": "d096afd3",
      "needsInterop": false
    },
    "@lobehub/icons": {
      "src": "../../node_modules/@lobehub/icons/es/index.js",
      "file": "@lobehub_icons.js",
      "fileHash": "a2a57893",
      "needsInterop": false
    },
    "react-fireworks": {
      "src": "../../node_modules/react-fireworks/react-fireworks.js",
      "file": "react-fireworks.js",
      "fileHash": "79202a7b",
      "needsInterop": false
    },
    "sse.js": {
      "src": "../../node_modules/sse.js/lib/sse.js",
      "file": "sse__js.js",
      "fileHash": "a23098df",
      "needsInterop": false
    },
    "prop-types": {
      "src": "../../node_modules/prop-types/index.js",
      "file": "prop-types.js",
      "fileHash": "455423ef",
      "needsInterop": true
    },
    "dayjs": {
      "src": "../../node_modules/dayjs/dayjs.min.js",
      "file": "dayjs.js",
      "fileHash": "cc2f6105",
      "needsInterop": true
    },
    "react-markdown": {
      "src": "../../node_modules/react-markdown/index.js",
      "file": "react-markdown.js",
      "fileHash": "14ab60a1",
      "needsInterop": false
    },
    "remark-math": {
      "src": "../../node_modules/remark-math/index.js",
      "file": "remark-math.js",
      "fileHash": "25730f42",
      "needsInterop": false
    },
    "remark-breaks": {
      "src": "../../node_modules/remark-breaks/index.js",
      "file": "remark-breaks.js",
      "fileHash": "43774aab",
      "needsInterop": false
    },
    "rehype-katex": {
      "src": "../../node_modules/rehype-katex/index.js",
      "file": "rehype-katex.js",
      "fileHash": "c34c1927",
      "needsInterop": false
    },
    "remark-gfm": {
      "src": "../../node_modules/remark-gfm/index.js",
      "file": "remark-gfm.js",
      "fileHash": "0193c6c1",
      "needsInterop": false
    },
    "rehype-highlight": {
      "src": "../../node_modules/rehype-highlight/index.js",
      "file": "rehype-highlight.js",
      "fileHash": "9158881d",
      "needsInterop": false
    },
    "mermaid": {
      "src": "../../node_modules/mermaid/dist/mermaid.core.mjs",
      "file": "mermaid.js",
      "fileHash": "e6c0e7c7",
      "needsInterop": false
    },
    "use-debounce": {
      "src": "../../node_modules/use-debounce/dist/index.module.js",
      "file": "use-debounce.js",
      "fileHash": "cca3d05b",
      "needsInterop": false
    },
    "clsx": {
      "src": "../../node_modules/clsx/dist/clsx.mjs",
      "file": "clsx.js",
      "fileHash": "d4f7d62f",
      "needsInterop": false
    },
    "qrcode.react": {
      "src": "../../node_modules/qrcode.react/lib/esm/index.js",
      "file": "qrcode__react.js",
      "fileHash": "5ad23c2d",
      "needsInterop": false
    },
    "react-icons/fa": {
      "src": "../../node_modules/react-icons/fa/index.mjs",
      "file": "react-icons_fa.js",
      "fileHash": "d8ecd6b1",
      "needsInterop": false
    }
  },
  "chunks": {
    "ishikawaDiagram-PHBUUO56-RK5SJRDD": {
      "file": "ishikawaDiagram-PHBUUO56-RK5SJRDD.js"
    },
    "vennDiagram-LZ73GAT5-6XV2EVPB": {
      "file": "vennDiagram-LZ73GAT5-6XV2EVPB.js"
    },
    "diagram-E7M64L7V-LVXVMMJ5": {
      "file": "diagram-E7M64L7V-LVXVMMJ5.js"
    },
    "timeline-definition-YZTLITO2-HX7C3KO4": {
      "file": "timeline-definition-YZTLITO2-HX7C3KO4.js"
    },
    "mindmap-definition-YRQLILUH-3MH2LOWV": {
      "file": "mindmap-definition-YRQLILUH-3MH2LOWV.js"
    },
    "kanban-definition-K7BYSVSG-6C7NVZPY": {
      "file": "kanban-definition-K7BYSVSG-6C7NVZPY.js"
    },
    "sankeyDiagram-WA2Y5GQK-ST64I4JU": {
      "file": "sankeyDiagram-WA2Y5GQK-ST64I4JU.js"
    },
    "diagram-P4PSJMXO-PYVWT4BC": {
      "file": "diagram-P4PSJMXO-PYVWT4BC.js"
    },
    "diagram-IFDJBPK2-YGMFTLIS": {
      "file": "diagram-IFDJBPK2-YGMFTLIS.js"
    },
    "blockDiagram-WCTKOSBZ-3CBYDROA": {
      "file": "blockDiagram-WCTKOSBZ-3CBYDROA.js"
    },
    "architectureDiagram-2XIMDMQ5-MSHYOR4V": {
      "file": "architectureDiagram-2XIMDMQ5-MSHYOR4V.js"
    },
    "xychartDiagram-JWTSCODW-QRB2UESO": {
      "file": "xychartDiagram-JWTSCODW-QRB2UESO.js"
    },
    "requirementDiagram-Z7DCOOCP-KD6AX7XT": {
      "file": "requirementDiagram-Z7DCOOCP-KD6AX7XT.js"
    },
    "sequenceDiagram-2WXFIKYE-IZH6EB5B": {
      "file": "sequenceDiagram-2WXFIKYE-IZH6EB5B.js"
    },
    "classDiagram-VBA2DB6C-KP7NS5M4": {
      "file": "classDiagram-VBA2DB6C-KP7NS5M4.js"
    },
    "classDiagram-v2-RAHNMMFH-KOVNIVBR": {
      "file": "classDiagram-v2-RAHNMMFH-KOVNIVBR.js"
    },
    "chunk-N33H4ZQ4": {
      "file": "chunk-N33H4ZQ4.js"
    },
    "stateDiagram-RAJIS63D-ITI3BU2F": {
      "file": "stateDiagram-RAJIS63D-ITI3BU2F.js"
    },
    "stateDiagram-v2-FVOUBMTO-VPREWSFL": {
      "file": "stateDiagram-v2-FVOUBMTO-VPREWSFL.js"
    },
    "chunk-E5MH7ENU": {
      "file": "chunk-E5MH7ENU.js"
    },
    "journeyDiagram-4ABVD52K-5XDKLTJE": {
      "file": "journeyDiagram-4ABVD52K-5XDKLTJE.js"
    },
    "gitGraph-HDMCJU4V-5ULUWG3S": {
      "file": "gitGraph-HDMCJU4V-5ULUWG3S.js"
    },
    "radar-KQ55EAFF-GILQIA7L": {
      "file": "radar-KQ55EAFF-GILQIA7L.js"
    },
    "treemap-KZPCXAKY-JZ4Z26VZ": {
      "file": "treemap-KZPCXAKY-JZ4Z26VZ.js"
    },
    "gitGraphDiagram-K3NZZRJ6-JLYOFOEX": {
      "file": "gitGraphDiagram-K3NZZRJ6-JLYOFOEX.js"
    },
    "chunk-M3YH6RFZ": {
      "file": "chunk-M3YH6RFZ.js"
    },
    "ganttDiagram-A5KZAMGK-DMIIDMED": {
      "file": "ganttDiagram-A5KZAMGK-DMIIDMED.js"
    },
    "infoDiagram-LFFYTUFH-Q3GW54F5": {
      "file": "infoDiagram-LFFYTUFH-Q3GW54F5.js"
    },
    "pieDiagram-SKSYHLDU-BELIWXTK": {
      "file": "pieDiagram-SKSYHLDU-BELIWXTK.js"
    },
    "chunk-H4T47UHL": {
      "file": "chunk-H4T47UHL.js"
    },
    "chunk-G7XXIRXJ": {
      "file": "chunk-G7XXIRXJ.js"
    },
    "chunk-NNNETVK7": {
      "file": "chunk-NNNETVK7.js"
    },
    "chunk-4YYWP455": {
      "file": "chunk-4YYWP455.js"
    },
    "chunk-MBVPKFPQ": {
      "file": "chunk-MBVPKFPQ.js"
    },
    "quadrantDiagram-337W2JSQ-JSR6ILKS": {
      "file": "quadrantDiagram-337W2JSQ-JSR6ILKS.js"
    },
    "cose-bilkent-S5V4N54A-BWPCBIXA": {
      "file": "cose-bilkent-S5V4N54A-BWPCBIXA.js"
    },
    "chunk-7KSWQE3Z": {
      "file": "chunk-7KSWQE3Z.js"
    },
    "c4Diagram-IC4MRINW-DI23XC3J": {
      "file": "c4Diagram-IC4MRINW-DI23XC3J.js"
    },
    "flowDiagram-PKNHOUZH-YQL22ML7": {
      "file": "flowDiagram-PKNHOUZH-YQL22ML7.js"
    },
    "chunk-62UX2E5G": {
      "file": "chunk-62UX2E5G.js"
    },
    "chunk-G2SSL45X": {
      "file": "chunk-G2SSL45X.js"
    },
    "erDiagram-INFDFZHY-WBWOUXFX": {
      "file": "erDiagram-INFDFZHY-WBWOUXFX.js"
    },
    "chunk-R3RKKDF4": {
      "file": "chunk-R3RKKDF4.js"
    },
    "chunk-CTM4C2AQ": {
      "file": "chunk-CTM4C2AQ.js"
    },
    "info-3K5VOQVL-PFJRJSY5": {
      "file": "info-3K5VOQVL-PFJRJSY5.js"
    },
    "chunk-KQJUE6OI": {
      "file": "chunk-KQJUE6OI.js"
    },
    "packet-RMMSAZCW-LEAUWP73": {
      "file": "packet-RMMSAZCW-LEAUWP73.js"
    },
    "chunk-RR5IXM4L": {
      "file": "chunk-RR5IXM4L.js"
    },
    "pie-UPGHQEXC-NCM37JJI": {
      "file": "pie-UPGHQEXC-NCM37JJI.js"
    },
    "chunk-2XR5FZ4C": {
      "file": "chunk-2XR5FZ4C.js"
    },
    "architecture-PBZL5I3N-YKBZPEDR": {
      "file": "architecture-PBZL5I3N-YKBZPEDR.js"
    },
    "chunk-2RDW5VCQ": {
      "file": "chunk-2RDW5VCQ.js"
    },
    "chunk-5SMYMPSU": {
      "file": "chunk-5SMYMPSU.js"
    },
    "vesper-42Q7LQMM": {
      "file": "vesper-42Q7LQMM.js"
    },
    "vitesse-black-YCFNVQPE": {
      "file": "vitesse-black-YCFNVQPE.js"
    },
    "vitesse-dark-FQVNFDV2": {
      "file": "vitesse-dark-FQVNFDV2.js"
    },
    "vitesse-light-SPI7NAKC": {
      "file": "vitesse-light-SPI7NAKC.js"
    },
    "wasm-LLAJEJLN": {
      "file": "wasm-LLAJEJLN.js"
    },
    "dist-YWFUQGOH": {
      "file": "dist-YWFUQGOH.js"
    },
    "katex-ZVP3U3DI": {
      "file": "katex-ZVP3U3DI.js"
    },
    "dagre-KLK3FWXG-BJOTLAIH": {
      "file": "dagre-KLK3FWXG-BJOTLAIH.js"
    },
    "chunk-5APHY2Y4": {
      "file": "chunk-5APHY2Y4.js"
    },
    "chunk-ZWCNTER3": {
      "file": "chunk-ZWCNTER3.js"
    },
    "rose-pine-moon-2GA3Z5HA": {
      "file": "rose-pine-moon-2GA3Z5HA.js"
    },
    "slack-dark-2BJYRHGN": {
      "file": "slack-dark-2BJYRHGN.js"
    },
    "slack-ochin-2X46JILO": {
      "file": "slack-ochin-2X46JILO.js"
    },
    "snazzy-light-VKA7ZZTK": {
      "file": "snazzy-light-VKA7ZZTK.js"
    },
    "solarized-dark-XOZEF7J3": {
      "file": "solarized-dark-XOZEF7J3.js"
    },
    "solarized-light-2DFMCYW3": {
      "file": "solarized-light-2DFMCYW3.js"
    },
    "synthwave-84-XCSEDTGG": {
      "file": "synthwave-84-XCSEDTGG.js"
    },
    "tokyo-night-ZOWY752J": {
      "file": "tokyo-night-ZOWY752J.js"
    },
    "nord-BLU2DC3V": {
      "file": "nord-BLU2DC3V.js"
    },
    "one-dark-pro-WMZEBZ4H": {
      "file": "one-dark-pro-WMZEBZ4H.js"
    },
    "one-light-UVMNEVPM": {
      "file": "one-light-UVMNEVPM.js"
    },
    "plastic-QRHHFLMW": {
      "file": "plastic-QRHHFLMW.js"
    },
    "poimandres-6YK3CSWI": {
      "file": "poimandres-6YK3CSWI.js"
    },
    "red-OVRUBC32": {
      "file": "red-OVRUBC32.js"
    },
    "rose-pine-WXE7JIXR": {
      "file": "rose-pine-WXE7JIXR.js"
    },
    "rose-pine-dawn-ISS7J46K": {
      "file": "rose-pine-dawn-ISS7J46K.js"
    },
    "material-theme-lighter-KM3POPUO": {
      "file": "material-theme-lighter-KM3POPUO.js"
    },
    "material-theme-ocean-23XXZUZ2": {
      "file": "material-theme-ocean-23XXZUZ2.js"
    },
    "material-theme-palenight-ATAKR4NS": {
      "file": "material-theme-palenight-ATAKR4NS.js"
    },
    "min-dark-NXTP76D5": {
      "file": "min-dark-NXTP76D5.js"
    },
    "min-light-VZ67Q7VJ": {
      "file": "min-light-VZ67Q7VJ.js"
    },
    "monokai-X7SP6YKU": {
      "file": "monokai-X7SP6YKU.js"
    },
    "night-owl-EJVB5GE4": {
      "file": "night-owl-EJVB5GE4.js"
    },
    "night-owl-light-F2644SZD": {
      "file": "night-owl-light-F2644SZD.js"
    },
    "houston-L2DTO5Z2": {
      "file": "houston-L2DTO5Z2.js"
    },
    "kanagawa-dragon-IKRJHLBC": {
      "file": "kanagawa-dragon-IKRJHLBC.js"
    },
    "kanagawa-lotus-VBFLJN2H": {
      "file": "kanagawa-lotus-VBFLJN2H.js"
    },
    "kanagawa-wave-ODFVEOU2": {
      "file": "kanagawa-wave-ODFVEOU2.js"
    },
    "laserwave-UV7T32KG": {
      "file": "laserwave-UV7T32KG.js"
    },
    "light-plus-GDOWPVIM": {
      "file": "light-plus-GDOWPVIM.js"
    },
    "material-theme-PUS4QEOA": {
      "file": "material-theme-PUS4QEOA.js"
    },
    "material-theme-darker-QJO3BZN2": {
      "file": "material-theme-darker-QJO3BZN2.js"
    },
    "gruvbox-dark-hard-N5IVZN6X": {
      "file": "gruvbox-dark-hard-N5IVZN6X.js"
    },
    "gruvbox-dark-medium-LO3ERCJD": {
      "file": "gruvbox-dark-medium-LO3ERCJD.js"
    },
    "gruvbox-dark-soft-IP27TGJP": {
      "file": "gruvbox-dark-soft-IP27TGJP.js"
    },
    "gruvbox-light-hard-2W5L3PLV": {
      "file": "gruvbox-light-hard-2W5L3PLV.js"
    },
    "gruvbox-light-medium-4RMZZRAW": {
      "file": "gruvbox-light-medium-4RMZZRAW.js"
    },
    "gruvbox-light-soft-7FBXGSVH": {
      "file": "gruvbox-light-soft-7FBXGSVH.js"
    },
    "horizon-DQORFE54": {
      "file": "horizon-DQORFE54.js"
    },
    "horizon-bright-7HT4IBX6": {
      "file": "horizon-bright-7HT4IBX6.js"
    },
    "everforest-light-IZQLJITU": {
      "file": "everforest-light-IZQLJITU.js"
    },
    "github-dark-TIEMIUJZ": {
      "file": "github-dark-TIEMIUJZ.js"
    },
    "github-dark-default-FW2TRAG6": {
      "file": "github-dark-default-FW2TRAG6.js"
    },
    "github-dark-dimmed-JYJIMDNB": {
      "file": "github-dark-dimmed-JYJIMDNB.js"
    },
    "github-dark-high-contrast-JKZG5W4P": {
      "file": "github-dark-high-contrast-JKZG5W4P.js"
    },
    "github-light-RJ6TJR34": {
      "file": "github-light-RJ6TJR34.js"
    },
    "github-light-default-CHEOPTN7": {
      "file": "github-light-default-CHEOPTN7.js"
    },
    "github-light-high-contrast-ERATJLPE": {
      "file": "github-light-high-contrast-ERATJLPE.js"
    },
    "catppuccin-frappe-JRND2OUE": {
      "file": "catppuccin-frappe-JRND2OUE.js"
    },
    "catppuccin-latte-TYK72ZKN": {
      "file": "catppuccin-latte-TYK72ZKN.js"
    },
    "catppuccin-macchiato-NZWHJNMM": {
      "file": "catppuccin-macchiato-NZWHJNMM.js"
    },
    "catppuccin-mocha-B64G5ICD": {
      "file": "catppuccin-mocha-B64G5ICD.js"
    },
    "dark-plus-RI37PO5H": {
      "file": "dark-plus-RI37PO5H.js"
    },
    "dracula-TGYMSWN6": {
      "file": "dracula-TGYMSWN6.js"
    },
    "dracula-soft-33AGPED4": {
      "file": "dracula-soft-33AGPED4.js"
    },
    "everforest-dark-AFB5RUEW": {
      "file": "everforest-dark-AFB5RUEW.js"
    },
    "xsl-HTCLHWH3": {
      "file": "xsl-HTCLHWH3.js"
    },
    "zenscript-32BB5MZS": {
      "file": "zenscript-32BB5MZS.js"
    },
    "zig-K23HMCAR": {
      "file": "zig-K23HMCAR.js"
    },
    "andromeeda-VPGFCJO2": {
      "file": "andromeeda-VPGFCJO2.js"
    },
    "aurora-x-P3RI2QR2": {
      "file": "aurora-x-P3RI2QR2.js"
    },
    "ayu-dark-MUVY7IFC": {
      "file": "ayu-dark-MUVY7IFC.js"
    },
    "ayu-light-IAQ2BKOW": {
      "file": "ayu-light-IAQ2BKOW.js"
    },
    "ayu-mirage-BFERL4JJ": {
      "file": "ayu-mirage-BFERL4JJ.js"
    },
    "vue-vine-ISCK7U75": {
      "file": "vue-vine-ISCK7U75.js"
    },
    "vyper-4HPTNGPP": {
      "file": "vyper-4HPTNGPP.js"
    },
    "wasm-WNWJOYQ4": {
      "file": "wasm-WNWJOYQ4.js"
    },
    "wenyan-HUSCHLCE": {
      "file": "wenyan-HUSCHLCE.js"
    },
    "wgsl-SJIQSXCB": {
      "file": "wgsl-SJIQSXCB.js"
    },
    "wikitext-34K3GNQC": {
      "file": "wikitext-34K3GNQC.js"
    },
    "wit-5ZAEGJD7": {
      "file": "wit-5ZAEGJD7.js"
    },
    "wolfram-DOQTX2VI": {
      "file": "wolfram-DOQTX2VI.js"
    },
    "v-YYMKRMTB": {
      "file": "v-YYMKRMTB.js"
    },
    "vala-4WUEEXH5": {
      "file": "vala-4WUEEXH5.js"
    },
    "vb-BH253FJU": {
      "file": "vb-BH253FJU.js"
    },
    "verilog-5VYVVCFJ": {
      "file": "verilog-5VYVVCFJ.js"
    },
    "vhdl-MJ2SNESH": {
      "file": "vhdl-MJ2SNESH.js"
    },
    "viml-KJMTV5V7": {
      "file": "viml-KJMTV5V7.js"
    },
    "vue-5IADJN4C": {
      "file": "vue-5IADJN4C.js"
    },
    "vue-html-EWHDKXN3": {
      "file": "vue-html-EWHDKXN3.js"
    },
    "templ-OXYPQMZL": {
      "file": "templ-OXYPQMZL.js"
    },
    "terraform-3Q3WJYE3": {
      "file": "terraform-3Q3WJYE3.js"
    },
    "toml-HORDSCIJ": {
      "file": "toml-HORDSCIJ.js"
    },
    "ts-tags-GRSZKFCP": {
      "file": "ts-tags-GRSZKFCP.js"
    },
    "tsv-JEUH47DA": {
      "file": "tsv-JEUH47DA.js"
    },
    "twig-QPALKXMQ": {
      "file": "twig-QPALKXMQ.js"
    },
    "typespec-VRYSFYAA": {
      "file": "typespec-VRYSFYAA.js"
    },
    "typst-LNZPCEQ7": {
      "file": "typst-LNZPCEQ7.js"
    },
    "surrealql-ACDWELWH": {
      "file": "surrealql-ACDWELWH.js"
    },
    "svelte-TE2GLU36": {
      "file": "svelte-TE2GLU36.js"
    },
    "swift-NRTWYG4A": {
      "file": "swift-NRTWYG4A.js"
    },
    "system-verilog-QPMJOE5H": {
      "file": "system-verilog-QPMJOE5H.js"
    },
    "systemd-NMRA3N6Z": {
      "file": "systemd-NMRA3N6Z.js"
    },
    "talonscript-FDIYLDBK": {
      "file": "talonscript-FDIYLDBK.js"
    },
    "tasl-RSCO3LLO": {
      "file": "tasl-RSCO3LLO.js"
    },
    "tcl-GQAQS6SX": {
      "file": "tcl-GQAQS6SX.js"
    },
    "solidity-KTID2DR6": {
      "file": "solidity-KTID2DR6.js"
    },
    "soy-FYMHMUQT": {
      "file": "soy-FYMHMUQT.js"
    },
    "turtle-F3KRCXCK": {
      "file": "turtle-F3KRCXCK.js"
    },
    "sparql-GETQKLY5": {
      "file": "sparql-GETQKLY5.js"
    },
    "chunk-Y6J44CJ7": {
      "file": "chunk-Y6J44CJ7.js"
    },
    "splunk-4LAIHKKU": {
      "file": "splunk-4LAIHKKU.js"
    },
    "ssh-config-QLYDODRW": {
      "file": "ssh-config-QLYDODRW.js"
    },
    "stata-4AMYM4DY": {
      "file": "stata-4AMYM4DY.js"
    },
    "stylus-OL7664DV": {
      "file": "stylus-OL7664DV.js"
    },
    "chunk-5YQASWT2": {
      "file": "chunk-5YQASWT2.js"
    },
    "rust-BOLITTNX": {
      "file": "rust-BOLITTNX.js"
    },
    "sas-ADM32ZNK": {
      "file": "sas-ADM32ZNK.js"
    },
    "sass-EKLR6DGA": {
      "file": "sass-EKLR6DGA.js"
    },
    "scala-7R2DVC4N": {
      "file": "scala-7R2DVC4N.js"
    },
    "scheme-3MYIJVDG": {
      "file": "scheme-3MYIJVDG.js"
    },
    "shaderlab-4Z2ZEZT6": {
      "file": "shaderlab-4Z2ZEZT6.js"
    },
    "shellsession-O4OY3F72": {
      "file": "shellsession-O4OY3F72.js"
    },
    "smalltalk-TJTACJL7": {
      "file": "smalltalk-TJTACJL7.js"
    },
    "raku-KDPX74TF": {
      "file": "raku-KDPX74TF.js"
    },
    "razor-3W42LKYC": {
      "file": "razor-3W42LKYC.js"
    },
    "reg-5UXA2PME": {
      "file": "reg-5UXA2PME.js"
    },
    "rel-EDPYSNVU": {
      "file": "rel-EDPYSNVU.js"
    },
    "riscv-IV2S7O5I": {
      "file": "riscv-IV2S7O5I.js"
    },
    "ron-XNH36RNV": {
      "file": "ron-XNH36RNV.js"
    },
    "rosmsg-275LCPIO": {
      "file": "rosmsg-275LCPIO.js"
    },
    "rst-J5KI3K5C": {
      "file": "rst-J5KI3K5C.js"
    },
    "proto-X3UF2X6A": {
      "file": "proto-X3UF2X6A.js"
    },
    "pug-U5UGO4WC": {
      "file": "pug-U5UGO4WC.js"
    },
    "puppet-RVFOKK2B": {
      "file": "puppet-RVFOKK2B.js"
    },
    "purescript-IUZBSQXJ": {
      "file": "purescript-IUZBSQXJ.js"
    },
    "qml-33X27DLX": {
      "file": "qml-33X27DLX.js"
    },
    "qmldir-TLHUJD4B": {
      "file": "qmldir-TLHUJD4B.js"
    },
    "qss-MH5AI4O6": {
      "file": "qss-MH5AI4O6.js"
    },
    "racket-CZN2X7JU": {
      "file": "racket-CZN2X7JU.js"
    },
    "pkl-SIHURKSI": {
      "file": "pkl-SIHURKSI.js"
    },
    "plsql-CLHNX3WE": {
      "file": "plsql-CLHNX3WE.js"
    },
    "po-P4VZN3J6": {
      "file": "po-P4VZN3J6.js"
    },
    "polar-OOVQPAVS": {
      "file": "polar-OOVQPAVS.js"
    },
    "powerquery-TH4PTYQB": {
      "file": "powerquery-TH4PTYQB.js"
    },
    "powershell-UWMUM2U6": {
      "file": "powershell-UWMUM2U6.js"
    },
    "prisma-D47MTB6T": {
      "file": "prisma-D47MTB6T.js"
    },
    "prolog-AKIPQIWB": {
      "file": "prolog-AKIPQIWB.js"
    },
    "nushell-XF42E5FS": {
      "file": "nushell-XF42E5FS.js"
    },
    "objective-c-PHASDOHW": {
      "file": "objective-c-PHASDOHW.js"
    },
    "objective-cpp-BE5Z4MCC": {
      "file": "objective-cpp-BE5Z4MCC.js"
    },
    "ocaml-WXJ27G2G": {
      "file": "ocaml-WXJ27G2G.js"
    },
    "odin-ALOU6P5V": {
      "file": "odin-ALOU6P5V.js"
    },
    "openscad-GW56NQTL": {
      "file": "openscad-GW56NQTL.js"
    },
    "pascal-WV5UX645": {
      "file": "pascal-WV5UX645.js"
    },
    "php-576FLBO6": {
      "file": "php-576FLBO6.js"
    },
    "chunk-WE3QFTV5": {
      "file": "chunk-WE3QFTV5.js"
    },
    "moonbit-TW6ZWOVQ": {
      "file": "moonbit-TW6ZWOVQ.js"
    },
    "move-JXDQ6KYG": {
      "file": "move-JXDQ6KYG.js"
    },
    "narrat-AOSFNCAT": {
      "file": "narrat-AOSFNCAT.js"
    },
    "nextflow-groovy-OAEOYSSE": {
      "file": "nextflow-groovy-OAEOYSSE.js"
    },
    "nextflow-H5HVZWZP": {
      "file": "nextflow-H5HVZWZP.js"
    },
    "chunk-VXBH7SXN": {
      "file": "chunk-VXBH7SXN.js"
    },
    "nginx-VRKKCCCF": {
      "file": "nginx-VRKKCCCF.js"
    },
    "nim-VCTZADZJ": {
      "file": "nim-VCTZADZJ.js"
    },
    "nix-DQRVHCPA": {
      "file": "nix-DQRVHCPA.js"
    },
    "make-PN6DU5XS": {
      "file": "make-PN6DU5XS.js"
    },
    "marko-FBM3MNFC": {
      "file": "marko-FBM3MNFC.js"
    },
    "matlab-VMBKCS3U": {
      "file": "matlab-VMBKCS3U.js"
    },
    "mdc-AUJJLW6F": {
      "file": "mdc-AUJJLW6F.js"
    },
    "mdx-7YCQ2IYF": {
      "file": "mdx-7YCQ2IYF.js"
    },
    "mermaid-YEI2LVXH": {
      "file": "mermaid-YEI2LVXH.js"
    },
    "mipsasm-KUSOSAHW": {
      "file": "mipsasm-KUSOSAHW.js"
    },
    "mojo-IFCO2SCG": {
      "file": "mojo-IFCO2SCG.js"
    },
    "latex-MHYDT4P4": {
      "file": "latex-MHYDT4P4.js"
    },
    "lean-2ZCJQCJN": {
      "file": "lean-2ZCJQCJN.js"
    },
    "less-5PUP4TER": {
      "file": "less-5PUP4TER.js"
    },
    "chunk-URFFN3TH": {
      "file": "chunk-URFFN3TH.js"
    },
    "liquid-5WCODQDH": {
      "file": "liquid-5WCODQDH.js"
    },
    "llvm-IP2F5VCR": {
      "file": "llvm-IP2F5VCR.js"
    },
    "log-D2SJYGOE": {
      "file": "log-D2SJYGOE.js"
    },
    "logo-2MIIIB2F": {
      "file": "logo-2MIIIB2F.js"
    },
    "luau-MHGZ4UJB": {
      "file": "luau-MHGZ4UJB.js"
    },
    "r-QHT4SONI": {
      "file": "r-QHT4SONI.js"
    },
    "julia-LRIW5NBB": {
      "file": "julia-LRIW5NBB.js"
    },
    "perl-YOMQE2PY": {
      "file": "perl-YOMQE2PY.js"
    },
    "just-3MCJPVTJ": {
      "file": "just-3MCJPVTJ.js"
    },
    "chunk-OPTR67VR": {
      "file": "chunk-OPTR67VR.js"
    },
    "kdl-XPH6JDZK": {
      "file": "kdl-XPH6JDZK.js"
    },
    "kotlin-L7FEWT6E": {
      "file": "kotlin-L7FEWT6E.js"
    },
    "kusto-KZI7BYKJ": {
      "file": "kusto-KZI7BYKJ.js"
    },
    "tex-MTS2FF4Z": {
      "file": "tex-MTS2FF4Z.js"
    },
    "chunk-ZST7QRJA": {
      "file": "chunk-ZST7QRJA.js"
    },
    "chunk-43EPIGJA": {
      "file": "chunk-43EPIGJA.js"
    },
    "ini-RTVGCK7B": {
      "file": "ini-RTVGCK7B.js"
    },
    "jinja-T2NRBHB3": {
      "file": "jinja-T2NRBHB3.js"
    },
    "jison-ATGCLGSY": {
      "file": "jison-ATGCLGSY.js"
    },
    "json5-PUN3PEA7": {
      "file": "json5-PUN3PEA7.js"
    },
    "jsonc-JOICVCX2": {
      "file": "jsonc-JOICVCX2.js"
    },
    "jsonl-OTDT7EQF": {
      "file": "jsonl-OTDT7EQF.js"
    },
    "jsonnet-UVKYD6OO": {
      "file": "jsonnet-UVKYD6OO.js"
    },
    "jssm-UPRG2B2L": {
      "file": "jssm-UPRG2B2L.js"
    },
    "hcl-UDPZ22G6": {
      "file": "hcl-UDPZ22G6.js"
    },
    "hjson-KBKQ7DZT": {
      "file": "hjson-KBKQ7DZT.js"
    },
    "hlsl-4N56DH74": {
      "file": "hlsl-4N56DH74.js"
    },
    "chunk-V3FAA7LG": {
      "file": "chunk-V3FAA7LG.js"
    },
    "http-2YJWKPXD": {
      "file": "http-2YJWKPXD.js"
    },
    "hurl-HZQG2556": {
      "file": "hurl-HZQG2556.js"
    },
    "hxml-H5CB5OPN": {
      "file": "hxml-H5CB5OPN.js"
    },
    "hy-MN7MBQPS": {
      "file": "hy-MN7MBQPS.js"
    },
    "imba-I34EFHYK": {
      "file": "imba-I34EFHYK.js"
    },
    "gn-WE5QAPQM": {
      "file": "gn-WE5QAPQM.js"
    },
    "gnuplot-QK72SYDD": {
      "file": "gnuplot-QK72SYDD.js"
    },
    "go-6KSJEQXN": {
      "file": "go-6KSJEQXN.js"
    },
    "chunk-ODQGJAJY": {
      "file": "chunk-ODQGJAJY.js"
    },
    "groovy-GLFUYOSZ": {
      "file": "groovy-GLFUYOSZ.js"
    },
    "hack-G4DQC5HF": {
      "file": "hack-G4DQC5HF.js"
    },
    "handlebars-QRDGJ2B3": {
      "file": "handlebars-QRDGJ2B3.js"
    },
    "haskell-LYB5AKRW": {
      "file": "haskell-LYB5AKRW.js"
    },
    "haxe-QBICSJEN": {
      "file": "haxe-QBICSJEN.js"
    },
    "chunk-OWX4C3JF": {
      "file": "chunk-OWX4C3JF.js"
    },
    "gdresource-MYZKA6XU": {
      "file": "gdresource-MYZKA6XU.js"
    },
    "genie-MWPGLU2W": {
      "file": "genie-MWPGLU2W.js"
    },
    "gherkin-ZOPYSABQ": {
      "file": "gherkin-ZOPYSABQ.js"
    },
    "git-commit-QLXAUKF6": {
      "file": "git-commit-QLXAUKF6.js"
    },
    "git-rebase-T4FISSCT": {
      "file": "git-rebase-T4FISSCT.js"
    },
    "gleam-YK5VSYYU": {
      "file": "gleam-YK5VSYYU.js"
    },
    "glimmer-js-W767USDC": {
      "file": "glimmer-js-W767USDC.js"
    },
    "glimmer-ts-XKLIKRLM": {
      "file": "glimmer-ts-XKLIKRLM.js"
    },
    "fennel-6IP4SAVT": {
      "file": "fennel-6IP4SAVT.js"
    },
    "fish-AWIGZNKZ": {
      "file": "fish-AWIGZNKZ.js"
    },
    "fluent-N7J3WH4F": {
      "file": "fluent-N7J3WH4F.js"
    },
    "fortran-free-form-CJNAXLDH": {
      "file": "fortran-free-form-CJNAXLDH.js"
    },
    "fortran-fixed-form-42SY7XTK": {
      "file": "fortran-fixed-form-42SY7XTK.js"
    },
    "chunk-NBPBOLGR": {
      "file": "chunk-NBPBOLGR.js"
    },
    "fsharp-QJC5WS2I": {
      "file": "fsharp-QJC5WS2I.js"
    },
    "gdshader-DB2NJVK3": {
      "file": "gdshader-DB2NJVK3.js"
    },
    "chunk-HX3BETJ5": {
      "file": "chunk-HX3BETJ5.js"
    },
    "gdscript-JYAXGUYK": {
      "file": "gdscript-JYAXGUYK.js"
    },
    "chunk-TNJQYQX3": {
      "file": "chunk-TNJQYQX3.js"
    },
    "jsx-LG4JDEC3": {
      "file": "jsx-LG4JDEC3.js"
    },
    "graphql-JOJ45GQO": {
      "file": "graphql-JOJ45GQO.js"
    },
    "lua-OFA4IHAY": {
      "file": "lua-OFA4IHAY.js"
    },
    "yaml-OSREZMJ6": {
      "file": "yaml-OSREZMJ6.js"
    },
    "ruby-J4775WBF": {
      "file": "ruby-J4775WBF.js"
    },
    "erb-QPVXPXM4": {
      "file": "erb-QPVXPXM4.js"
    },
    "chunk-BEQVXSFJ": {
      "file": "chunk-BEQVXSFJ.js"
    },
    "chunk-WZED4AWU": {
      "file": "chunk-WZED4AWU.js"
    },
    "chunk-WGBHRVG4": {
      "file": "chunk-WGBHRVG4.js"
    },
    "chunk-TO7J22CO": {
      "file": "chunk-TO7J22CO.js"
    },
    "chunk-ZYG2KGG3": {
      "file": "chunk-ZYG2KGG3.js"
    },
    "markdown-OLHA4QY6": {
      "file": "markdown-OLHA4QY6.js"
    },
    "erlang-Q6ZOLFQZ": {
      "file": "erlang-Q6ZOLFQZ.js"
    },
    "chunk-Z7XHXPFE": {
      "file": "chunk-Z7XHXPFE.js"
    },
    "docker-2PXN6BYE": {
      "file": "docker-2PXN6BYE.js"
    },
    "dotenv-CBSHKO7D": {
      "file": "dotenv-CBSHKO7D.js"
    },
    "dream-maker-BMMP33NR": {
      "file": "dream-maker-BMMP33NR.js"
    },
    "edge-JUQFIN63": {
      "file": "edge-JUQFIN63.js"
    },
    "elixir-7CF2ID2J": {
      "file": "elixir-7CF2ID2J.js"
    },
    "elm-YPM6E7LP": {
      "file": "elm-YPM6E7LP.js"
    },
    "emacs-lisp-2KOWECYR": {
      "file": "emacs-lisp-2KOWECYR.js"
    },
    "haml-AHGNS2GA": {
      "file": "haml-AHGNS2GA.js"
    },
    "chunk-OIBS6VKS": {
      "file": "chunk-OIBS6VKS.js"
    },
    "csv-FNL47VSU": {
      "file": "csv-FNL47VSU.js"
    },
    "chunk-5KWMBIKX": {
      "file": "chunk-5KWMBIKX.js"
    },
    "cue-2CIAXUSW": {
      "file": "cue-2CIAXUSW.js"
    },
    "cypher-4YTAPBTD": {
      "file": "cypher-4YTAPBTD.js"
    },
    "d-C43FSQMO": {
      "file": "d-C43FSQMO.js"
    },
    "dart-3IXBQYBR": {
      "file": "dart-3IXBQYBR.js"
    },
    "dax-FBUHXRXB": {
      "file": "dax-FBUHXRXB.js"
    },
    "desktop-E7AJ5YIQ": {
      "file": "desktop-E7AJ5YIQ.js"
    },
    "diff-OAO4DL4A": {
      "file": "diff-OAO4DL4A.js"
    },
    "chunk-LOCC3UBF": {
      "file": "chunk-LOCC3UBF.js"
    },
    "common-lisp-FJZPW6DE": {
      "file": "common-lisp-FJZPW6DE.js"
    },
    "coq-HSNQ73XZ": {
      "file": "coq-HSNQ73XZ.js"
    },
    "regexp-T4U6U4FR": {
      "file": "regexp-T4U6U4FR.js"
    },
    "glsl-W4FH3XNX": {
      "file": "glsl-W4FH3XNX.js"
    },
    "cpp-N27FMXFP": {
      "file": "cpp-N27FMXFP.js"
    },
    "chunk-R75LYVCW": {
      "file": "chunk-R75LYVCW.js"
    },
    "chunk-O5RPZYMG": {
      "file": "chunk-O5RPZYMG.js"
    },
    "chunk-TSPZ43CV": {
      "file": "chunk-TSPZ43CV.js"
    },
    "shellscript-5GL5ULIN": {
      "file": "shellscript-5GL5ULIN.js"
    },
    "crystal-HWKAVW6I": {
      "file": "crystal-HWKAVW6I.js"
    },
    "chunk-ST3CZ4LM": {
      "file": "chunk-ST3CZ4LM.js"
    },
    "csharp-GR5NUIH6": {
      "file": "csharp-GR5NUIH6.js"
    },
    "chunk-UAU2COIS": {
      "file": "chunk-UAU2COIS.js"
    },
    "cairo-XRS5GBOG": {
      "file": "cairo-XRS5GBOG.js"
    },
    "clarity-UYNUXINP": {
      "file": "clarity-UYNUXINP.js"
    },
    "clojure-FQ6RW754": {
      "file": "clojure-FQ6RW754.js"
    },
    "cmake-ERBNBVZZ": {
      "file": "cmake-ERBNBVZZ.js"
    },
    "chunk-SDNYNKCM": {
      "file": "chunk-SDNYNKCM.js"
    },
    "cobol-AUTKYFX5": {
      "file": "cobol-AUTKYFX5.js"
    },
    "codeowners-WUC6N7CL": {
      "file": "codeowners-WUC6N7CL.js"
    },
    "codeql-G5RSIRVC": {
      "file": "codeql-G5RSIRVC.js"
    },
    "coffee-F7MEFPWI": {
      "file": "coffee-F7MEFPWI.js"
    },
    "sql-YC57FP4F": {
      "file": "sql-YC57FP4F.js"
    },
    "blade-DH7LJFLH": {
      "file": "blade-DH7LJFLH.js"
    },
    "chunk-4KWBWBLU": {
      "file": "chunk-4KWBWBLU.js"
    },
    "sdbl-MMZBMZCY": {
      "file": "sdbl-MMZBMZCY.js"
    },
    "bsl-3OSDUGMJ": {
      "file": "bsl-3OSDUGMJ.js"
    },
    "chunk-A5EUPPUW": {
      "file": "chunk-A5EUPPUW.js"
    },
    "c-AWPG7OF6": {
      "file": "c-AWPG7OF6.js"
    },
    "chunk-2EKHLARE": {
      "file": "chunk-2EKHLARE.js"
    },
    "c3-U4RONVMB": {
      "file": "c3-U4RONVMB.js"
    },
    "cadence-AKGC4DDW": {
      "file": "cadence-AKGC4DDW.js"
    },
    "python-ADAP2L6J": {
      "file": "python-ADAP2L6J.js"
    },
    "chunk-VM7E4MQM": {
      "file": "chunk-VM7E4MQM.js"
    },
    "ballerina-2J475ZYV": {
      "file": "ballerina-2J475ZYV.js"
    },
    "bat-WX6ICVDZ": {
      "file": "bat-WX6ICVDZ.js"
    },
    "beancount-6OUSWEBG": {
      "file": "beancount-6OUSWEBG.js"
    },
    "berry-NBHVQCRD": {
      "file": "berry-NBHVQCRD.js"
    },
    "bibtex-MQA4KRVY": {
      "file": "bibtex-MQA4KRVY.js"
    },
    "bicep-5TRSZ7V6": {
      "file": "bicep-5TRSZ7V6.js"
    },
    "bird2-JYHHSLYS": {
      "file": "bird2-JYHHSLYS.js"
    },
    "html-derivative-KAGQSPFM": {
      "file": "html-derivative-KAGQSPFM.js"
    },
    "chunk-PEZGOGPJ": {
      "file": "chunk-PEZGOGPJ.js"
    },
    "ara-75RUISYE": {
      "file": "ara-75RUISYE.js"
    },
    "asciidoc-XSIULQOF": {
      "file": "asciidoc-XSIULQOF.js"
    },
    "asm-2LHBDD3D": {
      "file": "asm-2LHBDD3D.js"
    },
    "typescript-L4SFLTB7": {
      "file": "typescript-L4SFLTB7.js"
    },
    "postcss-OBIF3VKH": {
      "file": "postcss-OBIF3VKH.js"
    },
    "tsx-XYFHLQWP": {
      "file": "tsx-XYFHLQWP.js"
    },
    "astro-FCDWRVZJ": {
      "file": "astro-FCDWRVZJ.js"
    },
    "chunk-ZGT37PAW": {
      "file": "chunk-ZGT37PAW.js"
    },
    "chunk-F3ZVPNH5": {
      "file": "chunk-F3ZVPNH5.js"
    },
    "chunk-CQ35XRGX": {
      "file": "chunk-CQ35XRGX.js"
    },
    "awk-QNRUFZRH": {
      "file": "awk-QNRUFZRH.js"
    },
    "angular-ts-TAH5UR5S": {
      "file": "angular-ts-TAH5UR5S.js"
    },
    "apache-IJUH3VJG": {
      "file": "apache-IJUH3VJG.js"
    },
    "apex-HKUJJHT6": {
      "file": "apex-HKUJJHT6.js"
    },
    "java-RPX3NTN3": {
      "file": "java-RPX3NTN3.js"
    },
    "xml-BWJY2GDB": {
      "file": "xml-BWJY2GDB.js"
    },
    "json-H4RV6LQ6": {
      "file": "json-H4RV6LQ6.js"
    },
    "apl-XFFKR7NY": {
      "file": "apl-XFFKR7NY.js"
    },
    "chunk-PNPQ6EMK": {
      "file": "chunk-PNPQ6EMK.js"
    },
    "chunk-BDGTCZVY": {
      "file": "chunk-BDGTCZVY.js"
    },
    "chunk-AV4IQB23": {
      "file": "chunk-AV4IQB23.js"
    },
    "applescript-CHEUGLMH": {
      "file": "applescript-CHEUGLMH.js"
    },
    "abap-D4TFPP7L": {
      "file": "abap-D4TFPP7L.js"
    },
    "actionscript-3-L57YDRV5": {
      "file": "actionscript-3-L57YDRV5.js"
    },
    "ada-FF5F3FJY": {
      "file": "ada-FF5F3FJY.js"
    },
    "javascript-R4F65L3F": {
      "file": "javascript-R4F65L3F.js"
    },
    "css-VFHIS6FM": {
      "file": "css-VFHIS6FM.js"
    },
    "html-OP7XC5E7": {
      "file": "html-OP7XC5E7.js"
    },
    "angular-html-2GWR5BVK": {
      "file": "angular-html-2GWR5BVK.js"
    },
    "chunk-FLDYXSKJ": {
      "file": "chunk-FLDYXSKJ.js"
    },
    "chunk-BKLBPLLH": {
      "file": "chunk-BKLBPLLH.js"
    },
    "chunk-GFXZGBI4": {
      "file": "chunk-GFXZGBI4.js"
    },
    "scss-GMADQVSM": {
      "file": "scss-GMADQVSM.js"
    },
    "chunk-TMDR4QYJ": {
      "file": "chunk-TMDR4QYJ.js"
    },
    "chunk-BMBF3SKC": {
      "file": "chunk-BMBF3SKC.js"
    },
    "chunk-LGR27ENT": {
      "file": "chunk-LGR27ENT.js"
    },
    "chunk-7SGF32TO": {
      "file": "chunk-7SGF32TO.js"
    },
    "chunk-NBEFCHMA": {
      "file": "chunk-NBEFCHMA.js"
    },
    "chunk-I2HSE6D7": {
      "file": "chunk-I2HSE6D7.js"
    },
    "chunk-P32SJDBU": {
      "file": "chunk-P32SJDBU.js"
    },
    "chunk-5XJNJXN5": {
      "file": "chunk-5XJNJXN5.js"
    },
    "chunk-RK4ST7HX": {
      "file": "chunk-RK4ST7HX.js"
    },
    "chunk-2WVMAWKR": {
      "file": "chunk-2WVMAWKR.js"
    },
    "chunk-GCN5RWLQ": {
      "file": "chunk-GCN5RWLQ.js"
    },
    "chunk-KS234T37": {
      "file": "chunk-KS234T37.js"
    },
    "chunk-IPOIRDR2": {
      "file": "chunk-IPOIRDR2.js"
    },
    "chunk-O5N4F7PX": {
      "file": "chunk-O5N4F7PX.js"
    },
    "chunk-LQLXUK6X": {
      "file": "chunk-LQLXUK6X.js"
    },
    "chunk-OQUVF2X3": {
      "file": "chunk-OQUVF2X3.js"
    },
    "es-C3ZDTWJS": {
      "file": "es-C3ZDTWJS.js"
    },
    "chunk-QCDMX7LJ": {
      "file": "chunk-QCDMX7LJ.js"
    },
    "chunk-LNK32FLG": {
      "file": "chunk-LNK32FLG.js"
    },
    "chunk-Q5ACPU7L": {
      "file": "chunk-Q5ACPU7L.js"
    },
    "chunk-F64AUPJ6": {
      "file": "chunk-F64AUPJ6.js"
    },
    "chunk-ZXFBJHF7": {
      "file": "chunk-ZXFBJHF7.js"
    },
    "chunk-RMLN643Q": {
      "file": "chunk-RMLN643Q.js"
    },
    "chunk-J6ANVC7P": {
      "file": "chunk-J6ANVC7P.js"
    },
    "chunk-YFRUBO2K": {
      "file": "chunk-YFRUBO2K.js"
    },
    "chunk-KDVGFZWC": {
      "file": "chunk-KDVGFZWC.js"
    },
    "chunk-JTVSMKCA": {
      "file": "chunk-JTVSMKCA.js"
    },
    "chunk-SW2NX7BB": {
      "file": "chunk-SW2NX7BB.js"
    },
    "chunk-ZDFXAOV4": {
      "file": "chunk-ZDFXAOV4.js"
    },
    "chunk-RJSKXQCI": {
      "file": "chunk-RJSKXQCI.js"
    },
    "chunk-4K67LWXK": {
      "file": "chunk-4K67LWXK.js"
    },
    "chunk-X3YFS6D5": {
      "file": "chunk-X3YFS6D5.js"
    },
    "chunk-NKMVQ3UO": {
      "file": "chunk-NKMVQ3UO.js"
    },
    "chunk-4643Z7TA": {
      "file": "chunk-4643Z7TA.js"
    },
    "chunk-HAL2EMVM": {
      "file": "chunk-HAL2EMVM.js"
    },
    "chunk-F7NV6AHL": {
      "file": "chunk-F7NV6AHL.js"
    },
    "chunk-6BBHSHPJ": {
      "file": "chunk-6BBHSHPJ.js"
    },
    "chunk-GGEEJJAA": {
      "file": "chunk-GGEEJJAA.js"
    },
    "chunk-OM6ZERYF": {
      "file": "chunk-OM6ZERYF.js"
    },
    "chunk-J23NEJSF": {
      "file": "chunk-J23NEJSF.js"
    },
    "chunk-5CQLHWQW": {
      "file": "chunk-5CQLHWQW.js"
    },
    "chunk-BU3XFUIC": {
      "file": "chunk-BU3XFUIC.js"
    },
    "chunk-3KPFORGX": {
      "file": "chunk-3KPFORGX.js"
    },
    "chunk-SKNEHNFT": {
      "file": "chunk-SKNEHNFT.js"
    },
    "chunk-LGD7MII2": {
      "file": "chunk-LGD7MII2.js"
    },
    "chunk-FDCYYEZQ": {
      "file": "chunk-FDCYYEZQ.js"
    },
    "chunk-O7RNMSX7": {
      "file": "chunk-O7RNMSX7.js"
    },
    "chunk-AWUV36UU": {
      "file": "chunk-AWUV36UU.js"
    },
    "chunk-REUPNNPZ": {
      "file": "chunk-REUPNNPZ.js"
    },
    "chunk-6KNJ5NRM": {
      "file": "chunk-6KNJ5NRM.js"
    },
    "chunk-7IHLRR5V": {
      "file": "chunk-7IHLRR5V.js"
    },
    "chunk-AR4INM2Q": {
      "file": "chunk-AR4INM2Q.js"
    },
    "chunk-MIVMLEME": {
      "file": "chunk-MIVMLEME.js"
    },
    "chunk-PNM3REHP": {
      "file": "chunk-PNM3REHP.js"
    },
    "chunk-4EXITWLB": {
      "file": "chunk-4EXITWLB.js"
    },
    "chunk-ZKVPYPB3": {
      "file": "chunk-ZKVPYPB3.js"
    },
    "chunk-RXS6IDDQ": {
      "file": "chunk-RXS6IDDQ.js"
    },
    "chunk-6KWGA2CK": {
      "file": "chunk-6KWGA2CK.js"
    },
    "chunk-LI6IWGVD": {
      "file": "chunk-LI6IWGVD.js"
    },
    "chunk-SXNRNWGS": {
      "file": "chunk-SXNRNWGS.js"
    },
    "chunk-HQ6ZTAWL": {
      "file": "chunk-HQ6ZTAWL.js"
    },
    "chunk-HAKT4WWI": {
      "file": "chunk-HAKT4WWI.js"
    },
    "chunk-BUJ32E2A": {
      "file": "chunk-BUJ32E2A.js"
    },
    "chunk-ZJRFDPOD": {
      "file": "chunk-ZJRFDPOD.js"
    },
    "chunk-MG3PJ4UV": {
      "file": "chunk-MG3PJ4UV.js"
    },
    "chunk-M36Y5565": {
      "file": "chunk-M36Y5565.js"
    },
    "chunk-UE53HML6": {
      "file": "chunk-UE53HML6.js"
    }
  }
}